django_cheetahtemplate/__init__.py
django_cheetahtemplate-0.4.0.dist-info/METADATA
django_cheetahtemplate-0.4.0.dist-info/RECORD
django_cheetahtemplate-0.4.0.dist-info/WHEEL
django_cheetahtemplate-0.4.0.dist-info/top_level.txt
