Metadata-Version: 2.1
Name: django-cheetahtemplate
Version: 0.4.0
Summary: Use CheetahTemplate3 in Django
Home-page: https://github.com/CheetahTemplate3/django-cheetahtemplate
Author: Oleg Broytman
Author-email: phd@phdru.name
License: MIT
Project-URL: Download, https://pypi.org/pypi/django-cheetahtemplate
Project-URL: Issue tracker, https://github.com/CheetahTemplate3/django-cheetahtemplate/issues
Project-URL: Github repo, https://github.com/CheetahTemplate3/django-cheetahtemplate
Keywords: cheetah,django,template
Platform: Any
Classifier: Development Status :: 4 - Beta
Classifier: Intended Audience :: Developers
Classifier: Intended Audience :: System Administrators
Classifier: License :: OSI Approved :: MIT License
Classifier: Operating System :: OS Independent
Classifier: Programming Language :: Python :: Implementation :: CPython
Classifier: Programming Language :: Python
Classifier: Programming Language :: Python :: 2
Classifier: Programming Language :: Python :: 2.7
Classifier: Programming Language :: Python :: 3
Classifier: Programming Language :: Python :: 3.4
Classifier: Programming Language :: Python :: 3.5
Classifier: Programming Language :: Python :: 3.6
Classifier: Programming Language :: Python :: 3.7
Classifier: Programming Language :: Python :: 3.8
Classifier: Programming Language :: Python :: 3.9
Classifier: Programming Language :: Python :: 3.10
Classifier: Programming Language :: Python :: 3.11
Classifier: Topic :: Internet :: WWW/HTTP
Classifier: Topic :: Internet :: WWW/HTTP :: Dynamic Content
Classifier: Topic :: Internet :: WWW/HTTP :: Site Management
Classifier: Topic :: Software Development :: Code Generators
Classifier: Topic :: Software Development :: Libraries :: Python Modules
Classifier: Topic :: Software Development :: User Interfaces
Classifier: Topic :: Text Processing
Requires: Django
Requires: CT3
Requires-Python: >=2.7, !=3.0.*, !=3.1.*, !=3.2.*, !=3.3.*
Requires-Dist: CT3 (>=3.3)
Requires-Dist: Django (<2,>1.11); python_version == "2.7"
Requires-Dist: Django (<2.1,>=2); python_version == "3.4"
Requires-Dist: Django (>=2.2.25); python_version >= "3.5"
